viur/core/__init__.py
viur/core/cache.py
viur/core/config.py
viur/core/current.py
viur/core/decorators.py
viur/core/email.py
viur/core/errors.py
viur/core/i18n.py
viur/core/logging.py
viur/core/module.py
viur/core/pagination.py
viur/core/ratelimit.py
viur/core/request.py
viur/core/secret.py
viur/core/securityheaders.py
viur/core/securitykey.py
viur/core/session.py
viur/core/tasks.py
viur/core/version.py
viur/core/bones/__init__.py
viur/core/bones/base.py
viur/core/bones/boolean.py
viur/core/bones/captcha.py
viur/core/bones/color.py
viur/core/bones/credential.py
viur/core/bones/date.py
viur/core/bones/email.py
viur/core/bones/file.py
viur/core/bones/image.py
viur/core/bones/json.py
viur/core/bones/key.py
viur/core/bones/numeric.py
viur/core/bones/password.py
viur/core/bones/phone.py
viur/core/bones/randomslice.py
viur/core/bones/raw.py
viur/core/bones/record.py
viur/core/bones/relational.py
viur/core/bones/select.py
viur/core/bones/selectcountry.py
viur/core/bones/sortindex.py
viur/core/bones/spam.py
viur/core/bones/spatial.py
viur/core/bones/string.py
viur/core/bones/text.py
viur/core/bones/treeleaf.py
viur/core/bones/treenode.py
viur/core/bones/uid.py
viur/core/bones/uri.py
viur/core/bones/user.py
viur/core/db/__init__.py
viur/core/db/cache.py
viur/core/db/config.py
viur/core/db/overrides.py
viur/core/db/query.py
viur/core/db/transport.py
viur/core/db/types.py
viur/core/db/utils.py
viur/core/languages/__init__.py
viur/core/languages/de.py
viur/core/languages/en.py
viur/core/modules/__init__.py
viur/core/modules/file.py
viur/core/modules/formmailer.py
viur/core/modules/history.py
viur/core/modules/moduleconf.py
viur/core/modules/page.py
viur/core/modules/script.py
viur/core/modules/site.py
viur/core/modules/translation.py
viur/core/modules/user.py
viur/core/prototypes/__init__.py
viur/core/prototypes/instanced_module.py
viur/core/prototypes/list.py
viur/core/prototypes/singleton.py
viur/core/prototypes/skelmodule.py
viur/core/prototypes/tree.py
viur_core-3.8.15.dist-info/licenses/LICENSE
viur_core-3.8.15.dist-info/METADATA
viur_core-3.8.15.dist-info/WHEEL
viur_core-3.8.15.dist-info/entry_points.txt
viur_core-3.8.15.dist-info/top_level.txt
viur_core-3.8.15.dist-info/RECORD
