Metadata-Version: 2.4
Name: viur-core
Version: 3.8.15
Summary: The core component of ViUR, a development framework for Google App Engine
Author-email: Mausbrand Informationssysteme GmbH <devs@viur.dev>
Maintainer-email: Jan Max Meyer <jm@mausbrand.de>
License: Copyright © 2026 Mausbrand Informationssysteme GmbH
Project-URL: Homepage, https://www.viur.dev/
Project-URL: Documentation, https://core.docs.viur.dev/en/stable/
Project-URL: Repository, https://github.com/viur-framework/viur-core.git
Project-URL: Bug Tracker, https://github.com/viur-framework/viur-core/issues
Project-URL: Changelog, https://github.com/viur-framework/viur-core/blob/main/CHANGELOG.md
Keywords: viur,framework,backend
Classifier: Development Status :: 5 - Production/Stable
Classifier: Intended Audience :: Developers
Classifier: License :: OSI Approved :: MIT License
Classifier: Operating System :: OS Independent
Classifier: Programming Language :: Python :: 3.12
Classifier: Programming Language :: Python :: 3.13
Classifier: Topic :: Software Development :: Libraries :: Application Frameworks
Requires-Python: >=3.12
License-File: LICENSE
Requires-Dist: appengine-python-standard~=1.0
Requires-Dist: Deprecated~=1.2
Requires-Dist: google-api-core[grpc]~=2.0
Requires-Dist: google-auth~=2.0
Requires-Dist: google-cloud-bigquery~=3.0
Requires-Dist: google-cloud-datastore~=2.0
Requires-Dist: google-cloud-iam~=2.0
Requires-Dist: google-cloud-logging~=3.0
Requires-Dist: google-cloud-secret-manager~=2.0
Requires-Dist: google-cloud-storage~=2.0
Requires-Dist: google-cloud-tasks~=2.0
Requires-Dist: google-resumable-media~=2.0
Requires-Dist: googleapis-common-protos[grpc]~=1.0
Requires-Dist: gunicorn~=23.0
Requires-Dist: jinja2~=3.0
Requires-Dist: jsonschema~=4.0
Requires-Dist: logics-py==0.0.12
Requires-Dist: pillow~=11.0
Requires-Dist: pyotp~=2.0
Requires-Dist: pytz~=2023.0
Requires-Dist: pyyaml~=6.0
Requires-Dist: qrcode~=7.0
Requires-Dist: requests~=2.0
Requires-Dist: tzlocal~=5.0
Requires-Dist: urllib3==1.26.20
Requires-Dist: user-agents~=2.0
Requires-Dist: webob~=1.0
Provides-Extra: mailjet
Requires-Dist: mailjet-rest~=1.3; extra == "mailjet"
Provides-Extra: testing
Requires-Dist: coverage; extra == "testing"
Requires-Dist: coverage-badge; extra == "testing"
Dynamic: license-file
